{"radical": {"name": {"hiragana": "\u306f\u3053\u304c\u307e\u3048", "romaji": "hakogamae"}, "strokes": 2, "image": "https://media.kanjialive.com/radical_character/hakogamae.svg", "character": "\u2f15", "meaning": {"english": "box"}, "animation": ["https://media.kanjialive.com/rad_frames/hakogamae0.svg", "https://media.kanjialive.com/rad_frames/hakogamae1.svg", "https://media.kanjialive.com/rad_frames/hakogamae2.svg"], "position": {"hiragana": "\u304b\u307e\u3048, \u306f\u3053\u304c\u307e\u3048", "romaji": "kamae, hakogamae", "icon": "https://media.kanjialive.com/rad_positions/hakogamae.svg"}}, "kanji": {"strokes": {"count": 7, "images": ["https://media.kanjialive.com/kanji_strokes/i(gaku)_1.svg", "https://media.kanjialive.com/kanji_strokes/i(gaku)_2.svg", "https://media.kanjialive.com/kanji_strokes/i(gaku)_3.svg", "https://media.kanjialive.com/kanji_strokes/i(gaku)_4.svg", "https://media.kanjialive.com/kanji_strokes/i(gaku)_5.svg", "https://media.kanjialive.com/kanji_strokes/i(gaku)_6.svg", "https://media.kanjialive.com/kanji_strokes/i(gaku)_7.svg"], "timings": [0, 2.133, 3.066, 3.866, 4.733, 5.666, 6.466, 8.266667]}, "character": "\u533b", "kunyomi": {"hiragana": "n/a", "romaji": "n/a"}, "meaning": {"english": "medicine, doctor"}, "video": {"poster": "https://media.kanjialive.com/kanji_strokes/i(gaku)_7.svg", "mp4": "https://media.kanjialive.com/kanji_animations/kanji_mp4/i(gaku)_00.mp4", "webm": "https://media.kanjialive.com/kanji_animations/kanji_webm/i(gaku)_00.webm"}, "onyomi": {"katakana": "\u30a4", "romaji": "i"}}, "examples": [{"meaning": {"english": "doctor (medical)"}, "audio": {"opus": "https://media.kanjialive.com/examples_audio/audio-opus/i(gaku)_06_a.opus", "ogg": "https://media.kanjialive.com/examples_audio/audio-ogg/i(gaku)_06_a.ogg", "mp3": "https://media.kanjialive.com/examples_audio/audio-mp3/i(gaku)_06_a.mp3", "aac": "https://media.kanjialive.com/examples_audio/audio-aac/i(gaku)_06_a.aac"}, "japanese": "\u533b\u8005\uff08\u3044\u3057\u3083\uff09"}, {"meaning": {"english": "doctor (medical)"}, "audio": {"opus": "https://media.kanjialive.com/examples_audio/audio-opus/i(gaku)_06_b.opus", "ogg": "https://media.kanjialive.com/examples_audio/audio-ogg/i(gaku)_06_b.ogg", "mp3": "https://media.kanjialive.com/examples_audio/audio-mp3/i(gaku)_06_b.mp3", "aac": "https://media.kanjialive.com/examples_audio/audio-aac/i(gaku)_06_b.aac"}, "japanese": "\u533b\u5e2b\uff08\u3044\u3057\uff09"}, {"meaning": {"english": "medical care"}, "audio": {"opus": "https://media.kanjialive.com/examples_audio/audio-opus/i(gaku)_06_c.opus", "ogg": "https://media.kanjialive.com/examples_audio/audio-ogg/i(gaku)_06_c.ogg", "mp3": "https://media.kanjialive.com/examples_audio/audio-mp3/i(gaku)_06_c.mp3", "aac": "https://media.kanjialive.com/examples_audio/audio-aac/i(gaku)_06_c.aac"}, "japanese": "\u533b\u7642\uff08\u3044\u308a\u3087\u3046\uff09"}, {"meaning": {"english": "medical science"}, "audio": {"opus": "https://media.kanjialive.com/examples_audio/audio-opus/i(gaku)_06_d.opus", "ogg": "https://media.kanjialive.com/examples_audio/audio-ogg/i(gaku)_06_d.ogg", "mp3": "https://media.kanjialive.com/examples_audio/audio-mp3/i(gaku)_06_d.mp3", "aac": "https://media.kanjialive.com/examples_audio/audio-aac/i(gaku)_06_d.aac"}, "japanese": "\u533b\u5b66\uff08\u3044\u304c\u304f\uff09"}, {"meaning": {"english": "clinic"}, "audio": {"opus": "https://media.kanjialive.com/examples_audio/audio-opus/i(gaku)_06_e.opus", "ogg": "https://media.kanjialive.com/examples_audio/audio-ogg/i(gaku)_06_e.ogg", "mp3": "https://media.kanjialive.com/examples_audio/audio-mp3/i(gaku)_06_e.mp3", "aac": "https://media.kanjialive.com/examples_audio/audio-aac/i(gaku)_06_e.aac"}, "japanese": "\u533b\u9662\uff08\u3044\u3044\u3093\uff09"}, {"meaning": {"english": "medical supplies"}, "audio": {"opus": "https://media.kanjialive.com/examples_audio/audio-opus/i(gaku)_06_f.opus", "ogg": "https://media.kanjialive.com/examples_audio/audio-ogg/i(gaku)_06_f.ogg", "mp3": "https://media.kanjialive.com/examples_audio/audio-mp3/i(gaku)_06_f.mp3", "aac": "https://media.kanjialive.com/examples_audio/audio-aac/i(gaku)_06_f.aac"}, "japanese": "\u533b\u85ac\u54c1\uff08\u3044\u3084\u304f\u3072\u3093\uff09"}, {"meaning": {"english": "veterinarian"}, "audio": {"opus": "https://media.kanjialive.com/examples_audio/audio-opus/i(gaku)_06_g.opus", "ogg": "https://media.kanjialive.com/examples_audio/audio-ogg/i(gaku)_06_g.ogg", "mp3": "https://media.kanjialive.com/examples_audio/audio-mp3/i(gaku)_06_g.mp3", "aac": "https://media.kanjialive.com/examples_audio/audio-aac/i(gaku)_06_g.aac"}, "japanese": "\u7363\u533b\uff08\u3058\u3085\u3046\u3044\uff09"}, {"meaning": {"english": "dentist"}, "audio": {"opus": "https://media.kanjialive.com/examples_audio/audio-opus/i(gaku)_06_h.opus", "ogg": "https://media.kanjialive.com/examples_audio/audio-ogg/i(gaku)_06_h.ogg", "mp3": "https://media.kanjialive.com/examples_audio/audio-mp3/i(gaku)_06_h.mp3", "aac": "https://media.kanjialive.com/examples_audio/audio-aac/i(gaku)_06_h.aac"}, "japanese": "\u6b6f\u79d1\u533b\uff08\u3057\u304b\u3044\uff09"}], "references": {"grade": 3, "classic_nelson": "763", "kodansha": "1902"}}