{"radical": {"name": {"hiragana": "\u306b\u3093\u3079\u3093", "romaji": "ninben"}, "strokes": 2, "image": "https://media.kanjialive.com/radical_character/ninben.svg", "character": "\u2e85", "meaning": {"english": "person "}, "animation": ["https://media.kanjialive.com/rad_frames/ninben0.svg", "https://media.kanjialive.com/rad_frames/ninben1.svg", "https://media.kanjialive.com/rad_frames/ninben2.svg"], "position": {"hiragana": "\u3078\u3093", "romaji": "hen", "icon": "https://media.kanjialive.com/rad_positions/hen.svg"}}, "kanji": {"strokes": {"count": 9, "images": ["https://media.kanjialive.com/kanji_strokes/kei-kaka(ri)_1.svg", "https://media.kanjialive.com/kanji_strokes/kei-kaka(ri)_2.svg", "https://media.kanjialive.com/kanji_strokes/kei-kaka(ri)_3.svg", "https://media.kanjialive.com/kanji_strokes/kei-kaka(ri)_4.svg", "https://media.kanjialive.com/kanji_strokes/kei-kaka(ri)_5.svg", "https://media.kanjialive.com/kanji_strokes/kei-kaka(ri)_6.svg", "https://media.kanjialive.com/kanji_strokes/kei-kaka(ri)_7.svg", "https://media.kanjialive.com/kanji_strokes/kei-kaka(ri)_8.svg", "https://media.kanjialive.com/kanji_strokes/kei-kaka(ri)_9.svg"], "timings": [0.756, 1.312, 2.249, 3.319, 4.391, 5.464, 6.468, 7.34, 7.941, 8.782123]}, "character": "\u4fc2", "kunyomi": {"hiragana": "\u304b\u304b\u3001\u304b\u304b\u308a", "romaji": "kaka, kakaru, kakari, kakawaru, kakawari"}, "meaning": {"english": "connect, person in charge"}, "video": {"poster": "https://media.kanjialive.com/kanji_strokes/kei-kaka(ri)_9.svg", "mp4": "https://media.kanjialive.com/kanji_animations/kanji_mp4/kei-kaka(ri)_00.mp4", "webm": "https://media.kanjialive.com/kanji_animations/kanji_webm/kei-kaka(ri)_00.webm"}, "onyomi": {"katakana": "\u30b1\u30a4", "romaji": "kei"}}, "examples": [{"meaning": {"english": "be related to"}, "audio": {"opus": "https://media.kanjialive.com/examples_audio/audio-opus/kei-kaka(ri)_06_a.opus", "ogg": "https://media.kanjialive.com/examples_audio/audio-ogg/kei-kaka(ri)_06_a.ogg", "mp3": "https://media.kanjialive.com/examples_audio/audio-mp3/kei-kaka(ri)_06_a.mp3", "aac": "https://media.kanjialive.com/examples_audio/audio-aac/kei-kaka(ri)_06_a.aac"}, "japanese": "\u95a2\u4fc2\u3059\u308b\uff08\u304b\u3093\u3051\u3044\u3059\u308b\uff09"}, {"meaning": {"english": "work in a team"}, "audio": {"opus": "https://media.kanjialive.com/examples_audio/audio-opus/kei-kaka(ri)_06_b.opus", "ogg": "https://media.kanjialive.com/examples_audio/audio-ogg/kei-kaka(ri)_06_b.ogg", "mp3": "https://media.kanjialive.com/examples_audio/audio-mp3/kei-kaka(ri)_06_b.mp3", "aac": "https://media.kanjialive.com/examples_audio/audio-aac/kei-kaka(ri)_06_b.aac"}, "japanese": "\u9023\u4fc2\u3059\u308b\uff08\u308c\u3093\u3051\u3044\u3059\u308b\uff09"}, {"meaning": {"english": "affect, concern, depend on"}, "audio": {"opus": "https://media.kanjialive.com/examples_audio/audio-opus/kei-kaka(ri)_06_c.opus", "ogg": "https://media.kanjialive.com/examples_audio/audio-ogg/kei-kaka(ri)_06_c.ogg", "mp3": "https://media.kanjialive.com/examples_audio/audio-mp3/kei-kaka(ri)_06_c.mp3", "aac": "https://media.kanjialive.com/examples_audio/audio-aac/kei-kaka(ri)_06_c.aac"}, "japanese": "\u4fc2\u308b\uff08\u304b\u304b\u308b\uff09"}, {"meaning": {"english": "be involved"}, "audio": {"opus": "https://media.kanjialive.com/examples_audio/audio-opus/kei-kaka(ri)_06_d.opus", "ogg": "https://media.kanjialive.com/examples_audio/audio-ogg/kei-kaka(ri)_06_d.ogg", "mp3": "https://media.kanjialive.com/examples_audio/audio-mp3/kei-kaka(ri)_06_d.mp3", "aac": "https://media.kanjialive.com/examples_audio/audio-aac/kei-kaka(ri)_06_d.aac"}, "japanese": "\u4fc2\u308f\u308b\uff08\u304b\u304b\u308f\u308b\uff09"}, {"meaning": {"english": "person in charge"}, "audio": {"opus": "https://media.kanjialive.com/examples_audio/audio-opus/kei-kaka(ri)_06_e.opus", "ogg": "https://media.kanjialive.com/examples_audio/audio-ogg/kei-kaka(ri)_06_e.ogg", "mp3": "https://media.kanjialive.com/examples_audio/audio-mp3/kei-kaka(ri)_06_e.mp3", "aac": "https://media.kanjialive.com/examples_audio/audio-aac/kei-kaka(ri)_06_e.aac"}, "japanese": "\u4fc2\uff08\u304b\u304b\u308a\uff09"}, {"meaning": {"english": "clerk at the information desk"}, "audio": {"opus": "https://media.kanjialive.com/examples_audio/audio-opus/kei-kaka(ri)_06_f.opus", "ogg": "https://media.kanjialive.com/examples_audio/audio-ogg/kei-kaka(ri)_06_f.ogg", "mp3": "https://media.kanjialive.com/examples_audio/audio-mp3/kei-kaka(ri)_06_f.mp3", "aac": "https://media.kanjialive.com/examples_audio/audio-aac/kei-kaka(ri)_06_f.aac"}, "japanese": "\u6848\u5185\u4fc2\uff08\u3042\u3093\u306a\u3044\u304c\u304b\u308a\uff09"}], "references": {"grade": 3, "classic_nelson": "449", "kodansha": "73"}}