{"radical": {"name": {"hiragana": "\u304b\u306d\u3078\u3093", "romaji": "kanehen"}, "strokes": 8, "image": "https://media.kanjialive.com/radical_character/kanehen.svg", "character": "\ue717", "meaning": {"english": "metal, gold, mineral"}, "animation": ["https://media.kanjialive.com/rad_frames/kanehen0.svg", "https://media.kanjialive.com/rad_frames/kanehen1.svg", "https://media.kanjialive.com/rad_frames/kanehen2.svg"], "position": {"hiragana": "\u3078\u3093", "romaji": "hen", "icon": "https://media.kanjialive.com/rad_positions/hen.svg"}}, "kanji": {"strokes": {"count": 14, "images": ["https://media.kanjialive.com/kanji_strokes/dou(zou)_1.svg", "https://media.kanjialive.com/kanji_strokes/dou(zou)_2.svg", "https://media.kanjialive.com/kanji_strokes/dou(zou)_3.svg", "https://media.kanjialive.com/kanji_strokes/dou(zou)_4.svg", "https://media.kanjialive.com/kanji_strokes/dou(zou)_5.svg", "https://media.kanjialive.com/kanji_strokes/dou(zou)_6.svg", "https://media.kanjialive.com/kanji_strokes/dou(zou)_7.svg", "https://media.kanjialive.com/kanji_strokes/dou(zou)_8.svg", "https://media.kanjialive.com/kanji_strokes/dou(zou)_9.svg", "https://media.kanjialive.com/kanji_strokes/dou(zou)_10.svg", "https://media.kanjialive.com/kanji_strokes/dou(zou)_11.svg", "https://media.kanjialive.com/kanji_strokes/dou(zou)_12.svg", "https://media.kanjialive.com/kanji_strokes/dou(zou)_13.svg", "https://media.kanjialive.com/kanji_strokes/dou(zou)_14.svg"], "timings": [0, 1.266667, 2.333333, 3.066667, 4.133333, 5.266667, 5.866667, 6.466667, 7.6, 9.133333, 11.466667, 12.4, 13.133333, 14.2, 15.733333]}, "character": "\u9285", "kunyomi": {"hiragana": "n/a", "romaji": "n/a"}, "meaning": {"english": "copper"}, "video": {"poster": "https://media.kanjialive.com/kanji_strokes/dou(zou)_14.svg", "mp4": "https://media.kanjialive.com/kanji_animations/kanji_mp4/dou(zou)_00.mp4", "webm": "https://media.kanjialive.com/kanji_animations/kanji_webm/dou(zou)_00.webm"}, "onyomi": {"katakana": "\u30c9\u30a6", "romaji": "dou"}}, "examples": [{"meaning": {"english": "copper"}, "audio": {"opus": "https://media.kanjialive.com/examples_audio/audio-opus/dou(zou)_06_a.opus", "ogg": "https://media.kanjialive.com/examples_audio/audio-ogg/dou(zou)_06_a.ogg", "mp3": "https://media.kanjialive.com/examples_audio/audio-mp3/dou(zou)_06_a.mp3", "aac": "https://media.kanjialive.com/examples_audio/audio-aac/dou(zou)_06_a.aac"}, "japanese": "\u9285\uff08\u3069\u3046\uff09"}, {"meaning": {"english": "copper mine"}, "audio": {"opus": "https://media.kanjialive.com/examples_audio/audio-opus/dou(zou)_06_b.opus", "ogg": "https://media.kanjialive.com/examples_audio/audio-ogg/dou(zou)_06_b.ogg", "mp3": "https://media.kanjialive.com/examples_audio/audio-mp3/dou(zou)_06_b.mp3", "aac": "https://media.kanjialive.com/examples_audio/audio-aac/dou(zou)_06_b.aac"}, "japanese": "\u9285\u5c71\uff08\u3069\u3046\u3056\u3093\uff09"}, {"meaning": {"english": "copper coin"}, "audio": {"opus": "https://media.kanjialive.com/examples_audio/audio-opus/dou(zou)_06_c.opus", "ogg": "https://media.kanjialive.com/examples_audio/audio-ogg/dou(zou)_06_c.ogg", "mp3": "https://media.kanjialive.com/examples_audio/audio-mp3/dou(zou)_06_c.mp3", "aac": "https://media.kanjialive.com/examples_audio/audio-aac/dou(zou)_06_c.aac"}, "japanese": "\u9285\u8ca8\uff08\u3069\u3046\u304b\uff09"}, {"meaning": {"english": "bronze statue"}, "audio": {"opus": "https://media.kanjialive.com/examples_audio/audio-opus/dou(zou)_06_d.opus", "ogg": "https://media.kanjialive.com/examples_audio/audio-ogg/dou(zou)_06_d.ogg", "mp3": "https://media.kanjialive.com/examples_audio/audio-mp3/dou(zou)_06_d.mp3", "aac": "https://media.kanjialive.com/examples_audio/audio-aac/dou(zou)_06_d.aac"}, "japanese": "\u9285\u50cf\uff08\u3069\u3046\u305e\u3046\uff09"}, {"meaning": {"english": "bronze"}, "audio": {"opus": "https://media.kanjialive.com/examples_audio/audio-opus/dou(zou)_06_e.opus", "ogg": "https://media.kanjialive.com/examples_audio/audio-ogg/dou(zou)_06_e.ogg", "mp3": "https://media.kanjialive.com/examples_audio/audio-mp3/dou(zou)_06_e.mp3", "aac": "https://media.kanjialive.com/examples_audio/audio-aac/dou(zou)_06_e.aac"}, "japanese": "\u9752\u9285\uff08\u305b\u3044\u3069\u3046\uff09"}], "references": {"grade": 5, "classic_nelson": "4853", "kodansha": "1132"}}