{"radical": {"name": {"hiragana": "\u308a\u3063\u3057\u3093\u3079\u3093", "romaji": "risshinben"}, "strokes": 3, "image": "https://media.kanjialive.com/radical_character/risshinben.svg", "character": "\u2e96", "meaning": {"english": "heart, mind, spirit"}, "animation": ["https://media.kanjialive.com/rad_frames/risshinben0.svg", "https://media.kanjialive.com/rad_frames/risshinben1.svg", "https://media.kanjialive.com/rad_frames/risshinben2.svg"], "position": {"hiragana": "\u3078\u3093", "romaji": "hen", "icon": "https://media.kanjialive.com/rad_positions/hen.svg"}}, "kanji": {"strokes": {"count": 11, "images": ["https://media.kanjialive.com/kanji_strokes/nasa(ke)_1.svg", "https://media.kanjialive.com/kanji_strokes/nasa(ke)_2.svg", "https://media.kanjialive.com/kanji_strokes/nasa(ke)_3.svg", "https://media.kanjialive.com/kanji_strokes/nasa(ke)_4.svg", "https://media.kanjialive.com/kanji_strokes/nasa(ke)_5.svg", "https://media.kanjialive.com/kanji_strokes/nasa(ke)_6.svg", "https://media.kanjialive.com/kanji_strokes/nasa(ke)_7.svg", "https://media.kanjialive.com/kanji_strokes/nasa(ke)_8.svg", "https://media.kanjialive.com/kanji_strokes/nasa(ke)_9.svg", "https://media.kanjialive.com/kanji_strokes/nasa(ke)_10.svg", "https://media.kanjialive.com/kanji_strokes/nasa(ke)_11.svg"], "timings": [0.681, 1.35, 2.355, 3.493, 4.23, 4.968, 5.637, 6.911, 7.446, 8.786, 9.59, 10.117]}, "character": "\u60c5", "kunyomi": {"hiragana": "\u306a\u3055", "romaji": "nasa, nasake"}, "meaning": {"english": "emotion, actual conditions"}, "video": {"poster": "https://media.kanjialive.com/kanji_strokes/nasa(ke)_11.svg", "mp4": "https://media.kanjialive.com/kanji_animations/kanji_mp4/nasa(ke)_00.mp4", "webm": "https://media.kanjialive.com/kanji_animations/kanji_webm/nasa(ke)_00.webm"}, "onyomi": {"katakana": "\u30b8\u30e7\u30a6\u3001\u30bb\u30a4", "romaji": "jou, sei"}}, "examples": [{"meaning": {"english": "feelings"}, "audio": {"opus": "https://media.kanjialive.com/examples_audio/audio-opus/nasa(ke)_06_a.opus", "ogg": "https://media.kanjialive.com/examples_audio/audio-ogg/nasa(ke)_06_a.ogg", "mp3": "https://media.kanjialive.com/examples_audio/audio-mp3/nasa(ke)_06_a.mp3", "aac": "https://media.kanjialive.com/examples_audio/audio-aac/nasa(ke)_06_a.aac"}, "japanese": "\u60c5\uff08\u3058\u3087\u3046\uff09"}, {"meaning": {"english": "emotion(s)"}, "audio": {"opus": "https://media.kanjialive.com/examples_audio/audio-opus/nasa(ke)_06_b.opus", "ogg": "https://media.kanjialive.com/examples_audio/audio-ogg/nasa(ke)_06_b.ogg", "mp3": "https://media.kanjialive.com/examples_audio/audio-mp3/nasa(ke)_06_b.mp3", "aac": "https://media.kanjialive.com/examples_audio/audio-aac/nasa(ke)_06_b.aac"}, "japanese": "\u611f\u60c5\uff08\u304b\u3093\u3058\u3087\u3046\uff09"}, {"meaning": {"english": "love [n.]"}, "audio": {"opus": "https://media.kanjialive.com/examples_audio/audio-opus/nasa(ke)_06_c.opus", "ogg": "https://media.kanjialive.com/examples_audio/audio-ogg/nasa(ke)_06_c.ogg", "mp3": "https://media.kanjialive.com/examples_audio/audio-mp3/nasa(ke)_06_c.mp3", "aac": "https://media.kanjialive.com/examples_audio/audio-aac/nasa(ke)_06_c.aac"}, "japanese": "\u611b\u60c5\uff08\u3042\u3044\u3058\u3087\u3046\uff09"}, {"meaning": {"english": "friendship"}, "audio": {"opus": "https://media.kanjialive.com/examples_audio/audio-opus/nasa(ke)_06_d.opus", "ogg": "https://media.kanjialive.com/examples_audio/audio-ogg/nasa(ke)_06_d.ogg", "mp3": "https://media.kanjialive.com/examples_audio/audio-mp3/nasa(ke)_06_d.mp3", "aac": "https://media.kanjialive.com/examples_audio/audio-aac/nasa(ke)_06_d.aac"}, "japanese": "\u53cb\u60c5\uff08\u3086\u3046\u3058\u3087\u3046\uff09"}, {"meaning": {"english": "facial expression"}, "audio": {"opus": "https://media.kanjialive.com/examples_audio/audio-opus/nasa(ke)_06_e.opus", "ogg": "https://media.kanjialive.com/examples_audio/audio-ogg/nasa(ke)_06_e.ogg", "mp3": "https://media.kanjialive.com/examples_audio/audio-mp3/nasa(ke)_06_e.mp3", "aac": "https://media.kanjialive.com/examples_audio/audio-aac/nasa(ke)_06_e.aac"}, "japanese": "\u8868\u60c5\uff08\u3072\u3087\u3046\u3058\u3087\u3046\uff09"}, {"meaning": {"english": "circumstances"}, "audio": {"opus": "https://media.kanjialive.com/examples_audio/audio-opus/nasa(ke)_06_f.opus", "ogg": "https://media.kanjialive.com/examples_audio/audio-ogg/nasa(ke)_06_f.ogg", "mp3": "https://media.kanjialive.com/examples_audio/audio-mp3/nasa(ke)_06_f.mp3", "aac": "https://media.kanjialive.com/examples_audio/audio-aac/nasa(ke)_06_f.aac"}, "japanese": "\u4e8b\u60c5\uff08\u3058\u3058\u3087\u3046\uff09"}, {"meaning": {"english": "information"}, "audio": {"opus": "https://media.kanjialive.com/examples_audio/audio-opus/nasa(ke)_06_g.opus", "ogg": "https://media.kanjialive.com/examples_audio/audio-ogg/nasa(ke)_06_g.ogg", "mp3": "https://media.kanjialive.com/examples_audio/audio-mp3/nasa(ke)_06_g.mp3", "aac": "https://media.kanjialive.com/examples_audio/audio-aac/nasa(ke)_06_g.aac"}, "japanese": "\u60c5\u5831\uff08\u3058\u3087\u3046\u307b\u3046\uff09"}, {"meaning": {"english": "stubborn"}, "audio": {"opus": "https://media.kanjialive.com/examples_audio/audio-opus/nasa(ke)_06_h.opus", "ogg": "https://media.kanjialive.com/examples_audio/audio-ogg/nasa(ke)_06_h.ogg", "mp3": "https://media.kanjialive.com/examples_audio/audio-mp3/nasa(ke)_06_h.mp3", "aac": "https://media.kanjialive.com/examples_audio/audio-aac/nasa(ke)_06_h.aac"}, "japanese": "\u5f37\u60c5\u306a\uff08\u3054\u3046\u3058\u3087\u3046\u306a\uff09"}, {"meaning": {"english": "sympathize"}, "audio": {"opus": "https://media.kanjialive.com/examples_audio/audio-opus/nasa(ke)_06_i.opus", "ogg": "https://media.kanjialive.com/examples_audio/audio-ogg/nasa(ke)_06_i.ogg", "mp3": "https://media.kanjialive.com/examples_audio/audio-mp3/nasa(ke)_06_i.mp3", "aac": "https://media.kanjialive.com/examples_audio/audio-aac/nasa(ke)_06_i.aac"}, "japanese": "\u540c\u60c5\u3059\u308b\uff08\u3069\u3046\u3058\u3087\u3046\u3059\u308b\uff09"}, {"meaning": {"english": "taste, appearance"}, "audio": {"opus": "https://media.kanjialive.com/examples_audio/audio-opus/nasa(ke)_06_j.opus", "ogg": "https://media.kanjialive.com/examples_audio/audio-ogg/nasa(ke)_06_j.ogg", "mp3": "https://media.kanjialive.com/examples_audio/audio-mp3/nasa(ke)_06_j.mp3", "aac": "https://media.kanjialive.com/examples_audio/audio-aac/nasa(ke)_06_j.aac"}, "japanese": "\u98a8\u60c5\uff08\u3075\u305c\u3044\uff09"}, {"meaning": {"english": "sympathy, compassion"}, "audio": {"opus": "https://media.kanjialive.com/examples_audio/audio-opus/nasa(ke)_06_k.opus", "ogg": "https://media.kanjialive.com/examples_audio/audio-ogg/nasa(ke)_06_k.ogg", "mp3": "https://media.kanjialive.com/examples_audio/audio-mp3/nasa(ke)_06_k.mp3", "aac": "https://media.kanjialive.com/examples_audio/audio-aac/nasa(ke)_06_k.aac"}, "japanese": "\u60c5\u3051\uff08\u306a\u3055\u3051\uff09"}, {"meaning": {"english": "miserable, shameful"}, "audio": {"opus": "https://media.kanjialive.com/examples_audio/audio-opus/nasa(ke)_06_l.opus", "ogg": "https://media.kanjialive.com/examples_audio/audio-ogg/nasa(ke)_06_l.ogg", "mp3": "https://media.kanjialive.com/examples_audio/audio-mp3/nasa(ke)_06_l.mp3", "aac": "https://media.kanjialive.com/examples_audio/audio-aac/nasa(ke)_06_l.aac"}, "japanese": "\u60c5\u3051\u306a\u3044\uff08\u306a\u3055\u3051\u306a\u3044\uff09"}], "references": {"grade": 5, "classic_nelson": "1714", "kodansha": "353"}}