{"radical": {"name": {"hiragana": "\u306b\u3093\u3079\u3093", "romaji": "ninben"}, "strokes": 2, "image": "https://media.kanjialive.com/radical_character/ninben.svg", "character": "\u2e85", "meaning": {"english": "person "}, "animation": ["https://media.kanjialive.com/rad_frames/ninben0.svg", "https://media.kanjialive.com/rad_frames/ninben1.svg", "https://media.kanjialive.com/rad_frames/ninben2.svg"], "position": {"hiragana": "\u3078\u3093", "romaji": "hen", "icon": "https://media.kanjialive.com/rad_positions/hen.svg"}}, "kanji": {"strokes": {"count": 6, "images": ["https://media.kanjialive.com/kanji_strokes/tsuta(waru)_1.svg", "https://media.kanjialive.com/kanji_strokes/tsuta(waru)_2.svg", "https://media.kanjialive.com/kanji_strokes/tsuta(waru)_3.svg", "https://media.kanjialive.com/kanji_strokes/tsuta(waru)_4.svg", "https://media.kanjialive.com/kanji_strokes/tsuta(waru)_5.svg", "https://media.kanjialive.com/kanji_strokes/tsuta(waru)_6.svg"], "timings": [0, 1.6, 2.4, 3.466, 4.466, 5.733, 6.6]}, "character": "\u4f1d", "kunyomi": {"hiragana": "\u3064\u305f", "romaji": "tsuta, tsutawaru, tsutaeru, tsutau, tsutai"}, "meaning": {"english": "transmit"}, "video": {"poster": "https://media.kanjialive.com/kanji_strokes/tsuta(waru)_6.svg", "mp4": "https://media.kanjialive.com/kanji_animations/kanji_mp4/tsuta(waru)_00.mp4", "webm": "https://media.kanjialive.com/kanji_animations/kanji_webm/tsuta(waru)_00.webm"}, "onyomi": {"katakana": "\u30c7\u30f3", "romaji": "den"}}, "examples": [{"meaning": {"english": "tradition"}, "audio": {"opus": "https://media.kanjialive.com/examples_audio/audio-opus/tsuta(waru)_06_a.opus", "ogg": "https://media.kanjialive.com/examples_audio/audio-ogg/tsuta(waru)_06_a.ogg", "mp3": "https://media.kanjialive.com/examples_audio/audio-mp3/tsuta(waru)_06_a.mp3", "aac": "https://media.kanjialive.com/examples_audio/audio-aac/tsuta(waru)_06_a.aac"}, "japanese": "\u4f1d\u7d71\uff08\u3067\u3093\u3068\u3046\uff09"}, {"meaning": {"english": "tacit understanding"}, "audio": {"opus": "https://media.kanjialive.com/examples_audio/audio-opus/tsuta(waru)_06_b.opus", "ogg": "https://media.kanjialive.com/examples_audio/audio-ogg/tsuta(waru)_06_b.ogg", "mp3": "https://media.kanjialive.com/examples_audio/audio-mp3/tsuta(waru)_06_b.mp3", "aac": "https://media.kanjialive.com/examples_audio/audio-aac/tsuta(waru)_06_b.aac"}, "japanese": "\u4ee5\u5fc3\u4f1d\u5fc3\uff08\u3044\u3057\u3093\u3067\u3093\u3057\u3093\uff09"}, {"meaning": {"english": "convey message"}, "audio": {"opus": "https://media.kanjialive.com/examples_audio/audio-opus/tsuta(waru)_06_c.opus", "ogg": "https://media.kanjialive.com/examples_audio/audio-ogg/tsuta(waru)_06_c.ogg", "mp3": "https://media.kanjialive.com/examples_audio/audio-mp3/tsuta(waru)_06_c.mp3", "aac": "https://media.kanjialive.com/examples_audio/audio-aac/tsuta(waru)_06_c.aac"}, "japanese": "\u4f1d\u8a00\u3059\u308b\uff08\u3067\u3093\u3054\u3093\u3059\u308b\uff09"}, {"meaning": {"english": "convey (e.g. news)"}, "audio": {"opus": "https://media.kanjialive.com/examples_audio/audio-opus/tsuta(waru)_06_d.opus", "ogg": "https://media.kanjialive.com/examples_audio/audio-ogg/tsuta(waru)_06_d.ogg", "mp3": "https://media.kanjialive.com/examples_audio/audio-mp3/tsuta(waru)_06_d.mp3", "aac": "https://media.kanjialive.com/examples_audio/audio-aac/tsuta(waru)_06_d.aac"}, "japanese": "\u4f1d\u9054\u3059\u308b\uff08\u3067\u3093\u305f\u3064\u3059\u308b\uff09"}, {"meaning": {"english": "transmit (e.g. disease)"}, "audio": {"opus": "https://media.kanjialive.com/examples_audio/audio-opus/tsuta(waru)_06_e.opus", "ogg": "https://media.kanjialive.com/examples_audio/audio-ogg/tsuta(waru)_06_e.ogg", "mp3": "https://media.kanjialive.com/examples_audio/audio-mp3/tsuta(waru)_06_e.mp3", "aac": "https://media.kanjialive.com/examples_audio/audio-aac/tsuta(waru)_06_e.aac"}, "japanese": "\u4f1d\u67d3\u3059\u308b\uff08\u3067\u3093\u305b\u3093\u3059\u308b\uff09"}, {"meaning": {"english": "advertise"}, "audio": {"opus": "https://media.kanjialive.com/examples_audio/audio-opus/tsuta(waru)_06_f.opus", "ogg": "https://media.kanjialive.com/examples_audio/audio-ogg/tsuta(waru)_06_f.ogg", "mp3": "https://media.kanjialive.com/examples_audio/audio-mp3/tsuta(waru)_06_f.mp3", "aac": "https://media.kanjialive.com/examples_audio/audio-aac/tsuta(waru)_06_f.aac"}, "japanese": "\u5ba3\u4f1d\u3059\u308b\uff08\u305b\u3093\u3067\u3093\u3059\u308b\uff09"}, {"meaning": {"english": "be passed on (e.g. heredity)"}, "audio": {"opus": "https://media.kanjialive.com/examples_audio/audio-opus/tsuta(waru)_06_g.opus", "ogg": "https://media.kanjialive.com/examples_audio/audio-ogg/tsuta(waru)_06_g.ogg", "mp3": "https://media.kanjialive.com/examples_audio/audio-mp3/tsuta(waru)_06_g.mp3", "aac": "https://media.kanjialive.com/examples_audio/audio-aac/tsuta(waru)_06_g.aac"}, "japanese": "\u907a\u4f1d\u3059\u308b\uff08\u3044\u3067\u3093\u3059\u308b\uff09"}, {"meaning": {"english": "tell"}, "audio": {"opus": "https://media.kanjialive.com/examples_audio/audio-opus/tsuta(waru)_06_h.opus", "ogg": "https://media.kanjialive.com/examples_audio/audio-ogg/tsuta(waru)_06_h.ogg", "mp3": "https://media.kanjialive.com/examples_audio/audio-mp3/tsuta(waru)_06_h.mp3", "aac": "https://media.kanjialive.com/examples_audio/audio-aac/tsuta(waru)_06_h.aac"}, "japanese": "\u4f1d\u3048\u308b\uff08\u3064\u305f\u3048\u308b\uff09"}, {"meaning": {"english": "be transmitted"}, "audio": {"opus": "https://media.kanjialive.com/examples_audio/audio-opus/tsuta(waru)_06_i.opus", "ogg": "https://media.kanjialive.com/examples_audio/audio-ogg/tsuta(waru)_06_i.ogg", "mp3": "https://media.kanjialive.com/examples_audio/audio-mp3/tsuta(waru)_06_i.mp3", "aac": "https://media.kanjialive.com/examples_audio/audio-aac/tsuta(waru)_06_i.aac"}, "japanese": "\u4f1d\u308f\u308b\uff08\u3064\u305f\u308f\u308b\uff09"}, {"meaning": {"english": "assist"}, "audio": {"opus": "https://media.kanjialive.com/examples_audio/audio-opus/tsuta(waru)_06_j.opus", "ogg": "https://media.kanjialive.com/examples_audio/audio-ogg/tsuta(waru)_06_j.ogg", "mp3": "https://media.kanjialive.com/examples_audio/audio-mp3/tsuta(waru)_06_j.mp3", "aac": "https://media.kanjialive.com/examples_audio/audio-aac/tsuta(waru)_06_j.aac"}, "japanese": "\u624b\u4f1d\u3046\uff08\u3066\u3064\u3060\u3046\uff09"}], "references": {"grade": 4, "classic_nelson": "379", "kodansha": "28"}}