{"radical": {"name": {"hiragana": "\u3054\u3093\u3079\u3093", "romaji": "gonben"}, "strokes": 7, "image": "https://media.kanjialive.com/radical_character/gonben.svg", "character": "\ue704", "meaning": {"english": "words, to speak, say"}, "animation": ["https://media.kanjialive.com/rad_frames/gonben0.svg", "https://media.kanjialive.com/rad_frames/gonben1.svg", "https://media.kanjialive.com/rad_frames/gonben2.svg"], "position": {"hiragana": "\u3078\u3093", "romaji": "hen", "icon": "https://media.kanjialive.com/rad_positions/hen.svg"}}, "kanji": {"strokes": {"count": 10, "images": ["https://media.kanjialive.com/kanji_strokes/tou-u(tsu)_1.svg", "https://media.kanjialive.com/kanji_strokes/tou-u(tsu)_2.svg", "https://media.kanjialive.com/kanji_strokes/tou-u(tsu)_3.svg", "https://media.kanjialive.com/kanji_strokes/tou-u(tsu)_4.svg", "https://media.kanjialive.com/kanji_strokes/tou-u(tsu)_5.svg", "https://media.kanjialive.com/kanji_strokes/tou-u(tsu)_6.svg", "https://media.kanjialive.com/kanji_strokes/tou-u(tsu)_7.svg", "https://media.kanjialive.com/kanji_strokes/tou-u(tsu)_8.svg", "https://media.kanjialive.com/kanji_strokes/tou-u(tsu)_9.svg", "https://media.kanjialive.com/kanji_strokes/tou-u(tsu)_10.svg"], "timings": [0, 0.733333, 2.2, 3, 3.866667, 4.533333, 5.666667, 6.4, 8.4, 10.6, 11.933333]}, "character": "\u8a0e", "kunyomi": {"hiragana": "\u3046", "romaji": "u, utsu"}, "meaning": {"english": "attack, study, examine, discuss"}, "video": {"poster": "https://media.kanjialive.com/kanji_strokes/tou-u(tsu)_10.svg", "mp4": "https://media.kanjialive.com/kanji_animations/kanji_mp4/tou-u(tsu)_00.mp4", "webm": "https://media.kanjialive.com/kanji_animations/kanji_webm/tou-u(tsu)_00.webm"}, "onyomi": {"katakana": "\u30c8\u30a6", "romaji": "tou"}}, "examples": [{"meaning": {"english": "debate, discuss"}, "audio": {"opus": "https://media.kanjialive.com/examples_audio/audio-opus/tou-u(tsu)_06_a.opus", "ogg": "https://media.kanjialive.com/examples_audio/audio-ogg/tou-u(tsu)_06_a.ogg", "mp3": "https://media.kanjialive.com/examples_audio/audio-mp3/tou-u(tsu)_06_a.mp3", "aac": "https://media.kanjialive.com/examples_audio/audio-aac/tou-u(tsu)_06_a.aac"}, "japanese": "\u8a0e\u8b70\u3059\u308b\uff08\u3068\u3046\u304e\u3059\u308b\uff09"}, {"meaning": {"english": "debate, discuss"}, "audio": {"opus": "https://media.kanjialive.com/examples_audio/audio-opus/tou-u(tsu)_06_b.opus", "ogg": "https://media.kanjialive.com/examples_audio/audio-ogg/tou-u(tsu)_06_b.ogg", "mp3": "https://media.kanjialive.com/examples_audio/audio-mp3/tou-u(tsu)_06_b.mp3", "aac": "https://media.kanjialive.com/examples_audio/audio-aac/tou-u(tsu)_06_b.aac"}, "japanese": "\u8a0e\u8ad6\u3059\u308b\uff08\u3068\u3046\u308d\u3093\u3059\u308b\uff09"}, {"meaning": {"english": "subjugate, suppress"}, "audio": {"opus": "https://media.kanjialive.com/examples_audio/audio-opus/tou-u(tsu)_06_c.opus", "ogg": "https://media.kanjialive.com/examples_audio/audio-ogg/tou-u(tsu)_06_c.ogg", "mp3": "https://media.kanjialive.com/examples_audio/audio-mp3/tou-u(tsu)_06_c.mp3", "aac": "https://media.kanjialive.com/examples_audio/audio-aac/tou-u(tsu)_06_c.aac"}, "japanese": "\u8a0e\u4f10\u3059\u308b\uff08\u3068\u3046\u3070\u3064\u3059\u308b\uff09"}, {"meaning": {"english": "consider, examine"}, "audio": {"opus": "https://media.kanjialive.com/examples_audio/audio-opus/tou-u(tsu)_06_d.opus", "ogg": "https://media.kanjialive.com/examples_audio/audio-ogg/tou-u(tsu)_06_d.ogg", "mp3": "https://media.kanjialive.com/examples_audio/audio-mp3/tou-u(tsu)_06_d.mp3", "aac": "https://media.kanjialive.com/examples_audio/audio-aac/tou-u(tsu)_06_d.aac"}, "japanese": "\u691c\u8a0e\u3059\u308b\uff08\u3051\u3093\u3068\u3046\u3059\u308b\uff09"}, {"meaning": {"english": "attack, strike, shoot, avenge"}, "audio": {"opus": "https://media.kanjialive.com/examples_audio/audio-opus/tou-u(tsu)_06_e.opus", "ogg": "https://media.kanjialive.com/examples_audio/audio-ogg/tou-u(tsu)_06_e.ogg", "mp3": "https://media.kanjialive.com/examples_audio/audio-mp3/tou-u(tsu)_06_e.mp3", "aac": "https://media.kanjialive.com/examples_audio/audio-aac/tou-u(tsu)_06_e.aac"}, "japanese": "\u8a0e\u3064\uff08\u3046\u3064\uff09"}, {"meaning": {"english": "death in battle"}, "audio": {"opus": "https://media.kanjialive.com/examples_audio/audio-opus/tou-u(tsu)_06_f.opus", "ogg": "https://media.kanjialive.com/examples_audio/audio-ogg/tou-u(tsu)_06_f.ogg", "mp3": "https://media.kanjialive.com/examples_audio/audio-mp3/tou-u(tsu)_06_f.mp3", "aac": "https://media.kanjialive.com/examples_audio/audio-aac/tou-u(tsu)_06_f.aac"}, "japanese": "\u8a0e\u3061\u6b7b\u306b\uff08\u3046\u3061\u3058\u306b\uff09"}, {"meaning": {"english": "revenge [n.]"}, "audio": {"opus": "https://media.kanjialive.com/examples_audio/audio-opus/tou-u(tsu)_06_g.opus", "ogg": "https://media.kanjialive.com/examples_audio/audio-ogg/tou-u(tsu)_06_g.ogg", "mp3": "https://media.kanjialive.com/examples_audio/audio-mp3/tou-u(tsu)_06_g.mp3", "aac": "https://media.kanjialive.com/examples_audio/audio-aac/tou-u(tsu)_06_g.aac"}, "japanese": "\u6575\u8a0e\u3061\uff08\u304b\u305f\u304d\u3046\u3061\uff09"}, {"meaning": {"english": "surprise attack"}, "audio": {"opus": "https://media.kanjialive.com/examples_audio/audio-opus/tou-u(tsu)_06_h.opus", "ogg": "https://media.kanjialive.com/examples_audio/audio-ogg/tou-u(tsu)_06_h.ogg", "mp3": "https://media.kanjialive.com/examples_audio/audio-mp3/tou-u(tsu)_06_h.mp3", "aac": "https://media.kanjialive.com/examples_audio/audio-aac/tou-u(tsu)_06_h.aac"}, "japanese": "\u4e0d\u610f\u8a0e\u3061\uff08\u3075\u3044\u3046\u3061\uff09"}], "references": {"grade": 6, "classic_nelson": "4316", "kodansha": "977"}}